[
   {
      "id": 10,
      "fullName": "Emily",
      "age": 29,
      "gender": true,
      "birthday": "1996-07-25",
      "batch": { "id": 30, "batchName": "Batch_132" }
   },
   {
      "id": 11,
      "fullName": "John Doe",
      "age": 27,
      "gender": true,
      "birthday": "2018-07-18",
      "batch": { "id": 40, "batchName": "Batch_133" }
   },
   {
      "id": 12,
      "fullName": "Jane",
      "age": 23,
      "gender": false,
      "birthday": "1997-08-18",
      "batch": { "id": 40, "batchName": "Batch_133" }
   }
]
